HISTORY.rst
LICENSE.rst
MANIFEST.in
README.rst
setup.py
src/collective/__init__.py
src/collective.customicons.egg-info/PKG-INFO
src/collective.customicons.egg-info/SOURCES.txt
src/collective.customicons.egg-info/dependency_links.txt
src/collective.customicons.egg-info/entry_points.txt
src/collective.customicons.egg-info/namespace_packages.txt
src/collective.customicons.egg-info/requires.txt
src/collective.customicons.egg-info/top_level.txt
src/collective.customicons.egg-info/zip-safe
src/collective/customicons/__init__.py
src/collective/customicons/configure.zcml
src/collective/customicons/controlpanel.py
src/collective/customicons/indexer.py
src/collective/customicons/interfaces.py
src/collective/customicons/lookup.py
src/collective/customicons/utils.py
src/collective/customicons/at/__init__.py
src/collective/customicons/at/configure.zcml
src/collective/customicons/at/extender.py
src/collective/customicons/dx/__init__.py
src/collective/customicons/dx/behavior.py
src/collective/customicons/dx/configure.zcml
src/collective/customicons/profiles/default/browserlayer.xml
src/collective/customicons/profiles/default/controlpanel.xml
src/collective/customicons/profiles/default/metadata.xml
src/collective/customicons/profiles/default/registry.xml