Metadata-Version: 1.1
Name: collective.customicons
Version: 1.1
Summary: make custom icons available in plone
Home-page: http://github.com/collective/collective.customicons
Author: Jens Klein, Benjamin Stefaner
Author-email: jens@bluedynamics.com
License: GPLv2
Platform: UNKNOWN
Classifier: Development Status :: 5 - Production/Stable
Classifier: License :: OSI Approved :: GNU General Public License (GPL)
Classifier: Operating System :: OS Independent
Classifier: Programming Language :: Python
Classifier: Topic :: Software Development
Classifier: Framework :: Plone
